visbrain_sleep_port/__init__.py
visbrain_sleep_port/_pyqt_module.py
visbrain_sleep_port/config.py
visbrain_sleep_port/data_url.json
visbrain_sleep_port/gui/__init__.py
visbrain_sleep_port/gui/sleep/__init__.py
visbrain_sleep_port/gui/sleep/sleep.py
visbrain_sleep_port/gui/sleep/interface/__init__.py
visbrain_sleep_port/gui/sleep/interface/ui_init.py
visbrain_sleep_port/gui/sleep/interface/gui/__init__.py
visbrain_sleep_port/gui/sleep/interface/gui/sleep_gui.py
visbrain_sleep_port/gui/sleep/interface/ui_elements/__init__.py
visbrain_sleep_port/gui/sleep/interface/ui_elements/ui_annotate.py
visbrain_sleep_port/gui/sleep/interface/ui_elements/ui_detection.py
visbrain_sleep_port/gui/sleep/interface/ui_elements/ui_elements.py
visbrain_sleep_port/gui/sleep/interface/ui_elements/ui_info.py
visbrain_sleep_port/gui/sleep/interface/ui_elements/ui_menu.py
visbrain_sleep_port/gui/sleep/interface/ui_elements/ui_panels.py
visbrain_sleep_port/gui/sleep/interface/ui_elements/ui_scoring.py
visbrain_sleep_port/gui/sleep/interface/ui_elements/ui_screenshot.py
visbrain_sleep_port/gui/sleep/interface/ui_elements/ui_settings.py
visbrain_sleep_port/gui/sleep/interface/ui_elements/ui_tools.py
visbrain_sleep_port/gui/sleep/visuals/__init__.py
visbrain_sleep_port/gui/sleep/visuals/marker.py
visbrain_sleep_port/gui/sleep/visuals/visuals.py
visbrain_sleep_port/io/__init__.py
visbrain_sleep_port/io/dependencies.py
visbrain_sleep_port/io/dialog.py
visbrain_sleep_port/io/download.py
visbrain_sleep_port/io/mneio.py
visbrain_sleep_port/io/path.py
visbrain_sleep_port/io/read_annotations.py
visbrain_sleep_port/io/read_data.py
visbrain_sleep_port/io/read_sleep.py
visbrain_sleep_port/io/rw_config.py
visbrain_sleep_port/io/rw_hypno.py
visbrain_sleep_port/io/rw_nifti.py
visbrain_sleep_port/io/rw_utils.py
visbrain_sleep_port/io/write_data.py
visbrain_sleep_port/io/write_image.py
visbrain_sleep_port/io/write_table.py
visbrain_sleep_port/io/write_template.py
visbrain_sleep_port/mne/__init__.py
visbrain_sleep_port-0.0.1.dist-info/LICENSE
visbrain_sleep_port-0.0.1.dist-info/METADATA
visbrain_sleep_port-0.0.1.dist-info/WHEEL
visbrain_sleep_port-0.0.1.dist-info/top_level.txt
visbrain_sleep_port-0.0.1.dist-info/RECORD
