Metadata-Version: 2.1
Name: visbrain_sleep_port
Version: 0.0.1
Summary: Standalone version of Sleep module from Visbrain suite
Download-URL: https://github.com/EtienneCmb/visbrain/archive/v0.0.1.tar.gz
Author: Visbrain developers
Author-email: anjopag31@berkeley.edu
Maintainer: Anjo Pagdanganan
License: New BSD License
Keywords: brain MNI GPU visualization data OpenGL vispy neuroscience sleep data-mining
Platform: any
Classifier: Development Status :: 3 - Alpha
Classifier: Intended Audience :: Science/Research
Classifier: Intended Audience :: Education
Classifier: Intended Audience :: Developers
Classifier: Topic :: Scientific/Engineering :: Visualization
Classifier: Programming Language :: Python :: 3.5
Classifier: Programming Language :: Python :: 3.6
Classifier: Programming Language :: Python :: 3.7
Classifier: Operating System :: MacOS
Classifier: Operating System :: POSIX :: Linux
Classifier: Operating System :: Microsoft :: Windows
Classifier: Natural Language :: English
License-File: LICENSE
Requires-Dist: numpy >=1.13
Requires-Dist: scipy
Requires-Dist: vispy >=0.5.2
Requires-Dist: matplotlib >=1.5.5
Requires-Dist: pyqt5
Requires-Dist: pillow
Requires-Dist: PyOpenGL
Provides-Extra: full
Requires-Dist: mne ; extra == 'full'
Requires-Dist: tensorpac ; extra == 'full'
Requires-Dist: pandas ; extra == 'full'
Requires-Dist: xlrd ; extra == 'full'
Requires-Dist: scikit-image ; extra == 'full'
Requires-Dist: nibabel ; extra == 'full'
Provides-Extra: roi
Requires-Dist: pandas ; extra == 'roi'
Requires-Dist: xlrd ; extra == 'roi'
Provides-Extra: sleep
Requires-Dist: mne ; extra == 'sleep'
Requires-Dist: tensorpac ; extra == 'sleep'
Provides-Extra: topo
Requires-Dist: scikit-image ; extra == 'topo'
